echomimic/__init__.py
echomimic-0.0.1.dev0.dist-info/LICENSE
echomimic-0.0.1.dev0.dist-info/METADATA
echomimic-0.0.1.dev0.dist-info/WHEEL
echomimic-0.0.1.dev0.dist-info/top_level.txt
echomimic-0.0.1.dev0.dist-info/RECORD
