Metadata-Version: 2.1
Name: echomimic
Version: 0.0.1.dev0
Summary: echomimic
Author: Shadow Walker
Keywords: echomimic
Classifier: Programming Language :: Python :: 3
Classifier: Programming Language :: Python :: 3.8
Classifier: Programming Language :: Python :: 3.9
Classifier: Programming Language :: Python :: 3.10
License-File: LICENSE
